{"sprites":{"data":["64x64",0],"id":["64x64",1],"gold":["64x64",2],"silver":["64x64",3],"centcom":["64x64",4],"centcom_old":["64x64",5],"security":["64x64",6],"medical":["64x64",7],"HoS":["64x64",8],"research":["64x64",9],"cargo":["64x64",10],"engineering":["64x64",11],"CMO":["64x64",12],"RD":["64x64",13],"CE":["64x64",14],"clown":["64x64",15],"mime":["64x64",16],"rainbow":["64x64",17],"prisoner":["64x64",18],"commander":["64x64",19],"syndie":["64x64",20],"syndierd":["64x64",21],"syndiebotany":["64x64",22],"syndiecargo":["64x64",23],"syndiernd":["64x64",24],"syndieengineer":["64x64",25],"syndiechef":["64x64",26],"syndiemedical":["64x64",27],"deathsquad":["64x64",28],"ERT_leader":["64x64",29],"ERT_security":["64x64",30],"ERT_engineering":["64x64",31],"ERT_medical":["64x64",32],"ERT_janitorial":["64x64",33]}}